gpt2giga/__init__.py
gpt2giga/api_server.py
gpt2giga/auth.py
gpt2giga/cli.py
gpt2giga/config.py
gpt2giga/logger.py
gpt2giga/utils.py
gpt2giga/middlewares/__init__.py
gpt2giga/middlewares/pass_token.py
gpt2giga/middlewares/path_normalizer.py
gpt2giga/middlewares/rquid_context.py
gpt2giga/protocol/__init__.py
gpt2giga/protocol/attachments.py
gpt2giga/protocol/request_mapper.py
gpt2giga/protocol/response_mapper.py
gpt2giga/routers/__init__.py
gpt2giga/routers/api_router.py
gpt2giga/routers/system_router.py
gpt2giga/templates/log_viewer.html
gpt2giga-0.1.0.post0.dist-info/METADATA
gpt2giga-0.1.0.post0.dist-info/WHEEL
gpt2giga-0.1.0.post0.dist-info/entry_points.txt
gpt2giga-0.1.0.post0.dist-info/licenses/LICENSE
gpt2giga-0.1.0.post0.dist-info/RECORD
