Metadata-Version: 2.4
Name: gpt2giga
Version: 0.1.0.post0
Summary: Утилита для проксирования OpenAI-запросов в GigaChat
Author-email: Konstantin Krestnikov <rai220@gmail.com>
License-Expression: MIT
License-File: LICENSE
Requires-Python: <3.15,<4,>=3.10
Requires-Dist: aiohttp<4,>=3.10.10
Requires-Dist: aioitertools<0.14,>=0.13.0
Requires-Dist: fastapi<0.129.0,>=0.128.0
Requires-Dist: gigachat<0.3.0,>=0.2.0
Requires-Dist: loguru<0.8,>=0.7.3
Requires-Dist: openai<3,>=2.3.0
Requires-Dist: pillow<13,>=12
Requires-Dist: pydantic-settings<3,>=2.12.0
Requires-Dist: python-dotenv<2,>=1.0.1
Requires-Dist: sse-starlette<4,>=3.0.3
Requires-Dist: starlette<1,>=0.49
Requires-Dist: tiktoken<0.13,>=0.12.0
Requires-Dist: uvicorn<0.38,>=0.37.0
